absurd-0.0.8.dist-info/licenses/LICENSE
absurd_client/__init__.py
absurd-0.0.8.dist-info/METADATA
absurd-0.0.8.dist-info/WHEEL
absurd-0.0.8.dist-info/top_level.txt
absurd-0.0.8.dist-info/RECORD
